MANIFEST.in
README.md
setup.py
bayerstraits_16s/__init__.py
bayerstraits_16s/__main__.py
bayerstraits_16s.egg-info/PKG-INFO
bayerstraits_16s.egg-info/SOURCES.txt
bayerstraits_16s.egg-info/dependency_links.txt
bayerstraits_16s.egg-info/entry_points.txt
bayerstraits_16s.egg-info/top_level.txt
bayerstraits_16s/data/.DS_Store
bayerstraits_16s/data/.Rhistory
bayerstraits_16s/data/GMC_CG_16S.fasta
bayerstraits_16s/data/GMC_CG_buk_ptbORbut.txt
bayerstraits_16s/data/GMC_CG_pathogen.txt
bayerstraits_16s/data/GMC_CG_species.txt
bayerstraits_16s/example/.example.otu_seqs.icloud
bayerstraits_16s/example/.example.otu_table.icloud
bayerstraits_16s/scripts/.DS_Store
bayerstraits_16s/scripts/Bayers.model.py
bayerstraits_16s/scripts/Bayers.model.species.py
bayerstraits_16s/scripts/OTU.filter.py
bayerstraits_16s/scripts/inferTraits.py
bayerstraits_16s/scripts/inferTraits_species.py
bayerstraits_16s/scripts/treeformat.py